README.md
setup.py
keap_flask/__init__.py
keap_flask/consts.py
keap_flask/keapcache.py
keap_flask/keapclient.py
keap_flask/keaprestclient.py
keap_flask/keapsession.py
keap_flask.egg-info/PKG-INFO
keap_flask.egg-info/SOURCES.txt
keap_flask.egg-info/dependency_links.txt
keap_flask.egg-info/requires.txt
keap_flask.egg-info/top_level.txt